transly/__init__.py
transly/__pycache__/__init__.cpython-37.pyc
transly/base/__init__.py
transly/base/config.py
transly/base/model.py
transly/base/__pycache__/__init__.cpython-37.pyc
transly/base/__pycache__/config.cpython-37.pyc
transly/base/__pycache__/model.cpython-37.pyc
transly/pronunciation/__init__.py
transly/pronunciation/pronunciation.py
transly/pronunciation/__pycache__/__init__.cpython-37.pyc
transly/pronunciation/__pycache__/pronunciation.cpython-37.pyc
transly/pronunciation/trained_models/cmu/config.pkl
transly/pronunciation/trained_models/cmu/model.h5
transly/pronunciation/training_data/cmu.csv
transly/seq2seq/__init__.py
transly/seq2seq/config.py
transly/seq2seq/seq2seq.py
transly/seq2seq/version0.py
transly/seq2seq/version1.py
transly/seq2seq/__pycache__/__init__.cpython-37.pyc
transly/seq2seq/__pycache__/config.cpython-37.pyc
transly/seq2seq/__pycache__/seq2seq.cpython-37.pyc
transly/seq2seq/__pycache__/version0.cpython-37.pyc
transly/seq2seq/__pycache__/version1.cpython-37.pyc
transly/transliteration/__init__.py
transly/transliteration/transliteration.py
transly/transliteration/__pycache__/__init__.cpython-37.pyc
transly/transliteration/__pycache__/transliteration.cpython-37.pyc
transly/transliteration/trained_models/en2hi/config.pkl
transly/transliteration/trained_models/en2hi/model.h5
transly/transliteration/trained_models/hi2en/config.pkl
transly/transliteration/trained_models/hi2en/model.h5
transly/transliteration/training_data/hi2en.csv
transly-0.1.3.dist-info/LICENSE
transly-0.1.3.dist-info/METADATA
transly-0.1.3.dist-info/WHEEL
transly-0.1.3.dist-info/top_level.txt
transly-0.1.3.dist-info/RECORD
