Metadata-Version: 2.1
Name: transly
Version: 0.1.3
Summary: Pronunciation and Transliteration module trained on CMU pronouncing dictionary, IIT Bombay and IIT Kharagpur text corpora
Home-page: https://github.com/gitnik17/transly
Author: Nikhil Kothari
Author-email: gitnik17@gmail.com
License: Apache License 2.0
Platform: UNKNOWN
Classifier: Programming Language :: Python :: 3
Requires-Dist: pandas
Requires-Dist: keras (==2.3.1)
Requires-Dist: setuptools
Requires-Dist: tensorflow (==2.1.0)
Requires-Dist: h5py (==2.10.0)
